pyopenwebui/__init__.py
pyopenwebui/_base_client.py
pyopenwebui/_client.py
pyopenwebui/_compat.py
pyopenwebui/_constants.py
pyopenwebui/_exceptions.py
pyopenwebui/_files.py
pyopenwebui/_models.py
pyopenwebui/_qs.py
pyopenwebui/_resource.py
pyopenwebui/_response.py
pyopenwebui/_streaming.py
pyopenwebui/_types.py
pyopenwebui/_version.py
pyopenwebui/py.typed
pyopenwebui/_utils/__init__.py
pyopenwebui/_utils/_logs.py
pyopenwebui/_utils/_proxy.py
pyopenwebui/_utils/_reflection.py
pyopenwebui/_utils/_streams.py
pyopenwebui/_utils/_sync.py
pyopenwebui/_utils/_transform.py
pyopenwebui/_utils/_typing.py
pyopenwebui/_utils/_utils.py
pyopenwebui/lib/.keep
pyopenwebui/resources/__init__.py
pyopenwebui/resources/health.py
pyopenwebui/resources/manifest_json.py
pyopenwebui/resources/oauth.py
pyopenwebui/resources/opensearch_xml.py
pyopenwebui/resources/api/__init__.py
pyopenwebui/resources/api/api.py
pyopenwebui/resources/api/chat.py
pyopenwebui/resources/api/models.py
pyopenwebui/resources/api/tasks.py
pyopenwebui/resources/api/version.py
pyopenwebui/resources/api/webhook.py
pyopenwebui/resources/api/v1/__init__.py
pyopenwebui/resources/api/v1/folders.py
pyopenwebui/resources/api/v1/memories.py
pyopenwebui/resources/api/v1/v1.py
pyopenwebui/resources/api/v1/audio/__init__.py
pyopenwebui/resources/api/v1/audio/audio.py
pyopenwebui/resources/api/v1/audio/config.py
pyopenwebui/resources/api/v1/auths/__init__.py
pyopenwebui/resources/api/v1/auths/api_key.py
pyopenwebui/resources/api/v1/auths/auths.py
pyopenwebui/resources/api/v1/auths/update.py
pyopenwebui/resources/api/v1/auths/admin/__init__.py
pyopenwebui/resources/api/v1/auths/admin/admin.py
pyopenwebui/resources/api/v1/auths/admin/config/__init__.py
pyopenwebui/resources/api/v1/auths/admin/config/config.py
pyopenwebui/resources/api/v1/auths/admin/config/ldap/__init__.py
pyopenwebui/resources/api/v1/auths/admin/config/ldap/ldap.py
pyopenwebui/resources/api/v1/auths/admin/config/ldap/server.py
pyopenwebui-0.5.0.dist-info/METADATA
pyopenwebui-0.5.0.dist-info/WHEEL
pyopenwebui-0.5.0.dist-info/licenses/LICENSE
pyopenwebui-0.5.0.dist-info/RECORD
